{"id": "mecca and the soul brother", "name": "Mecca and the Soul Brother", "consensus_translation": "麦加与灵魂兄弟", "category": "专辑", "alias": "", "group": "", "author": "Pete Rock & C. L. Smooth", "album": "", "date": "1992", "language": "en", "wikipedia": {"pageid": 3939226, "ns": 0, "title": "Mecca and the Soul Brother", "extract": "Mecca and the Soul Brother is the 1992 debut album from the Mount Vernon, New York hip-hop duo, Pete Rock & CL Smooth. The album contains their best known song, \"They Reminisce Over You (T.R.O.Y.)\". Mecca and the Soul Brother has been widely acclaimed as one of the greatest hip hop albums of all time. The album was mostly produced by Pete Rock and executive produced by DJ Eddie F of Heavy D & the Boyz (co-group member with Trouble T-Roy)."}, "opinions": [{"user_name": "mimida", "github_handle": "idmimida", "translation": "麦加与灵魂兄弟", "details": ""}]}