{"id": "too short", "name": "Too Short", "consensus_translation": "太矮", "category": "乐人", "alias": "", "group": "", "author": "", "album": "", "date": "", "language": "en", "wikipedia": {"pageid": 294515, "ns": 0, "title": "Too Short", "extract": "Todd Anthony Shaw (born April 28, 1966), better known by the stage name Too Short (stylized as Too $hort), is an American rapper and record producer famous for his rap lyrics' focus on pimping, promiscuity, drug culture, street survival, as in the songs \"The Ghetto\" and \"Blow the Whistle\".\nA pioneer of West Coast rap, he began recording in 1983, drew renown on Oakland's underground rap scene, and signed a major deal in 1987 with Jive Records, which released his album Born to Mack. In 1989, his sophomore album, Life Is...Too Short, drew wide notice, and he remained prominent into the 1990s.\n\n"}, "opinions": [{"user_name": "mimida", "github_handle": "idmimida", "translation": "太矮", "details": ""}]}