{"id": "underground resistance", "name": "Underground Resistance", "consensus_translation": "地下抵抗", "category": "乐人", "alias": "", "group": "", "author": "", "album": "", "date": "", "language": "en", "wikipedia": {"pageid": 1292361, "ns": 0, "title": "Underground Resistance", "extract": "Underground Resistance (commonly abbreviated to UR) are a musical collective from Detroit, Michigan, United States. Producing primarily Detroit techno since 1990 with a grungy four-track musical aesthetic, they are also renowned for their militant political and anti-corporate ethos."}, "opinions": [{"user_name": "mimida", "github_handler": "idmimida", "translation": "地下抵抗", "details": ""}]}